mcp_data_analyse/__init__.py
mcp_data_analyse/__main__.py
mcp_data_analyse/cli.py
mcp_data_analyse/core.py
mcp_data_analyse/my_tools.py
my_data_analyse-0.1.4.dist-info/METADATA
my_data_analyse-0.1.4.dist-info/WHEEL
my_data_analyse-0.1.4.dist-info/entry_points.txt
my_data_analyse-0.1.4.dist-info/top_level.txt
my_data_analyse-0.1.4.dist-info/RECORD
